mloader/__init__.py
mloader/__main__.py
mloader/__version__.py
mloader/constants.py
mloader/exporter.py
mloader/loader.py
mloader/response_pb2.py
mloader/utils.py
mloader-1.1.12.dist-info/LICENSE
mloader-1.1.12.dist-info/METADATA
mloader-1.1.12.dist-info/WHEEL
mloader-1.1.12.dist-info/entry_points.txt
mloader-1.1.12.dist-info/top_level.txt
mloader-1.1.12.dist-info/RECORD
