Metadata-Version: 2.1
Name: mloader
Version: 1.1.12
Summary: Command-line tool to download manga from mangaplus
Home-page: https://github.com/hurlenko/mloader
License: GPLv3
Project-URL: Source, https://github.com/hurlenko/mloader
Platform: UNKNOWN
Classifier: License :: OSI Approved :: GNU General Public License v3 (GPLv3)
Classifier: Programming Language :: Python
Classifier: Programming Language :: Python :: 3.5
Classifier: Programming Language :: Python :: 3.6
Classifier: Programming Language :: Python :: 3.7
Classifier: Programming Language :: Python :: 3.8
Classifier: Programming Language :: Python :: 3.9
Classifier: Programming Language :: Python :: 3.10
Classifier: Programming Language :: Python :: Implementation :: CPython
Requires-Python: >=3.6
Requires-Dist: Click >=6.2
Requires-Dist: protobuf ~=3.6
Requires-Dist: requests >=2
